<?xml version="1.0" encoding="utf-8" ?>
<dwsync>
<file name="color_picker.js" server="C:/AppServ/www/cms/" local="129458371460000000" remote="129458371460000000" />
<file name="openAsset.gif" server="C:/AppServ/www/cms/" local="127371517200000000" remote="127371517200000000" />
<file name="img_reset.gif" server="C:/AppServ/www/cms/" local="127407099600000000" remote="127407099600000000" />
<file name="img.gif" server="C:/AppServ/www/cms/" local="127408960200000000" remote="127408960200000000" />
<file name="blank.gif" server="C:/AppServ/www/cms/" local="127105616400000000" remote="127105616400000000" />
<file name="bookmark.htm" server="C:/AppServ/www/cms/" local="128977255880000000" remote="128977255880000000" />
<file name="border.htm" server="C:/AppServ/www/cms/" local="128991913160000000" remote="128991913160000000" />
<file name="box.htm" server="C:/AppServ/www/cms/" local="128991917320000000" remote="128991917320000000" />
<file name="characters.htm" server="C:/AppServ/www/cms/" local="128977344260000000" remote="128977344260000000" />
<file name="color_picker.htm" server="C:/AppServ/www/cms/" local="129451666980000000" remote="129451666980000000" />
<file name="color_picker_bg.htm" server="C:/AppServ/www/cms/" local="128968701120000000" remote="128968701120000000" />
<file name="color_picker_fg.htm" server="C:/AppServ/www/cms/" local="128968701060000000" remote="128968701060000000" />
<file name="default_edit.css" server="C:/AppServ/www/cms/" local="128971187060000000" remote="128971187060000000" />
<file name="dropbtn.gif" server="C:/AppServ/www/cms/" local="127496001600000000" remote="127496001600000000" />
<file name="editor.js" server="C:/AppServ/www/cms/" local="129469716020000000" remote="129469716020000000" />
<file name="editor_source.js" server="C:/AppServ/www/cms/" local="129469715080000000" remote="129469715080000000" />
<file name="flash.htm" server="C:/AppServ/www/cms/" local="128991922920000000" remote="128991922920000000" />
<file name="form_button.htm" server="C:/AppServ/www/cms/" local="128977374320000000" remote="128977374320000000" />
<file name="form_check.htm" server="C:/AppServ/www/cms/" local="128977374480000000" remote="128977374480000000" />
<file name="form_file.htm" server="C:/AppServ/www/cms/" local="128977371040000000" remote="128977371040000000" />
<file name="form_form.htm" server="C:/AppServ/www/cms/" local="128977372180000000" remote="128977372180000000" />
<file name="form_hidden.htm" server="C:/AppServ/www/cms/" local="128977372400000000" remote="128977372400000000" />
<file name="form_list.htm" server="C:/AppServ/www/cms/" local="128977372620000000" remote="128977372620000000" />
<file name="form_radio.htm" server="C:/AppServ/www/cms/" local="128977372880000000" remote="128977372880000000" />
<file name="form_text.htm" server="C:/AppServ/www/cms/" local="128977373160000000" remote="128977373160000000" />
<file name="hyperlink.htm" server="C:/AppServ/www/cms/" local="129294421240000000" remote="129294421240000000" />
<file name="image.htm" server="C:/AppServ/www/cms/" local="129470692800000000" remote="129470692800000000" />
<file name="image_background.htm" server="C:/AppServ/www/cms/" local="128977395400000000" remote="128977395400000000" />
<file name="list.htm" server="C:/AppServ/www/cms/" local="129125122840000000" remote="129125122840000000" />
<file name="list.js" server="C:/AppServ/www/cms/" local="128273219620000000" remote="128273219620000000" />
<file name="media.htm" server="C:/AppServ/www/cms/" local="128977385220000000" remote="128977385220000000" />
<file name="paragraph.htm" server="C:/AppServ/www/cms/" local="128977393280000000" remote="128977393280000000" />
<file name="paste_text.htm" server="C:/AppServ/www/cms/" local="128977407460000000" remote="128977407460000000" />
<file name="paste_word.htm" server="C:/AppServ/www/cms/" local="129006582040000000" remote="129006582040000000" />
<file name="preview.htm" server="C:/AppServ/www/cms/" local="128977408640000000" remote="128977408640000000" />
<file name="search.htm" server="C:/AppServ/www/cms/" local="128977410700000000" remote="128977410700000000" />
<file name="search2.htm" server="C:/AppServ/www/cms/" local="128977416220000000" remote="128977416220000000" />
<file name="source_html.htm" server="C:/AppServ/www/cms/" local="128977413920000000" remote="128977413920000000" />
<file name="source_html_full.htm" server="C:/AppServ/www/cms/" local="129235370800000000" remote="129235370800000000" />
<file name="source_xhtml.htm" server="C:/AppServ/www/cms/" local="129469771500000000" remote="129469771500000000" />
<file name="source_xhtml_full.htm" server="C:/AppServ/www/cms/" local="129469771840000000" remote="129469771840000000" />
<file name="spellcheck2.htm" server="C:/AppServ/www/cms/" local="128968737640000000" remote="128968737640000000" />
<file name="styles_cssText.htm" server="C:/AppServ/www/cms/" local="128977424880000000" remote="128977424880000000" />
<file name="table.js" server="C:/AppServ/www/cms/" local="128968751040000000" remote="128968751040000000" />
<file name="table_edit.htm" server="C:/AppServ/www/cms/" local="129161220660000000" remote="129161220660000000" />
<file name="table_editCell.htm" server="C:/AppServ/www/cms/" local="129449829200000000" remote="129449829200000000" />
<file name="table_format.htm" server="C:/AppServ/www/cms/" local="129421439680000000" remote="129421439680000000" />
<file name="table_insert.htm" server="C:/AppServ/www/cms/" local="129006550560000000" remote="129006550560000000" />
<file name="table_size.htm" server="C:/AppServ/www/cms/" local="128977435240000000" remote="128977435240000000" />
<file name="text1.htm" server="C:/AppServ/www/cms/" local="129125118380000000" remote="129125118380000000" />
<file name="text2.htm" server="C:/AppServ/www/cms/" local="129125118840000000" remote="129125118840000000" />
<file name="webdrop.js" server="C:/AppServ/www/cms/" local="128273219600000000" remote="128273219600000000" />
<file name="youtube_video.htm" server="C:/AppServ/www/cms/" local="129421436600000000" remote="129421436600000000" />
</dwsync>